dizqueTV/PYTHON_VERSIONS.json
dizqueTV/__init__.py
dizqueTV/_info.py
dizqueTV/advanced.py
dizqueTV/decorators.py
dizqueTV/dizquetv.py
dizqueTV/dizquetv_logging.py
dizqueTV/dizquetv_requests.py
dizqueTV/exceptions.py
dizqueTV/helpers.py
dizqueTV/plex_utils.py
dizqueTV/models/__init__.py
dizqueTV/models/base.py
dizqueTV/models/channels.py
dizqueTV/models/custom_show.py
dizqueTV/models/fillers.py
dizqueTV/models/general.py
dizqueTV/models/guide.py
dizqueTV/models/media.py
dizqueTV/models/plex_server.py
dizqueTV/models/settings.py
dizqueTV/models/templates.py
dizquetv-2.2.0.170.dist-info/licenses/LICENSE
dizquetv-2.2.0.170.dist-info/METADATA
dizquetv-2.2.0.170.dist-info/WHEEL
dizquetv-2.2.0.170.dist-info/top_level.txt
dizquetv-2.2.0.170.dist-info/RECORD
