Metadata-Version: 2.4
Name: dizqueTV
Version: 2.2.0.170
Summary: Interact with a dizqueTV instance's API
Home-page: https://github.com/nwithan8/dizqueTV-python
Download-URL: https://github.com/nwithan8/dizqueTV-python/archive/refs/tags/2.2.0.170.tar.gz
Author: Nate Harris
Author-email: n8gr8gbln@gmail.com
License: GNU General Public License v3 (GPLv3)
Keywords: dizqueTV,Plex,Jellyfin,Emby,media,API,server,interaction,TV,television,streaming
Classifier: License :: OSI Approved :: GNU General Public License v3 (GPLv3)
Classifier: Development Status :: 4 - Beta
Classifier: Intended Audience :: Developers
Classifier: Topic :: Software Development :: Build Tools
Classifier: Topic :: Multimedia :: Video
Classifier: Topic :: Multimedia
Classifier: Topic :: Internet :: WWW/HTTP
Classifier: Operating System :: OS Independent
Classifier: Programming Language :: Python :: 3
Classifier: Programming Language :: Python :: 3.10
Classifier: Programming Language :: Python :: 3.11
Classifier: Programming Language :: Python :: 3.12
Classifier: Programming Language :: Python :: 3.13
Classifier: Programming Language :: Python :: 3.14
Requires-Python: >=3.10, <4
License-File: LICENSE
Requires-Dist: m3u8==3.*
Requires-Dist: PlexAPI==4.*; python_version >= "3.6"
Requires-Dist: numpy==1.*
Requires-Dist: objectrest==1.*
Provides-Extra: dev
Requires-Dist: black; extra == "dev"
Requires-Dist: flake8; extra == "dev"
Requires-Dist: isort; extra == "dev"
Requires-Dist: pytest-cov==3.*; extra == "dev"
Requires-Dist: pytest==7.*; extra == "dev"
Requires-Dist: types-requests; extra == "dev"
Requires-Dist: types-urllib3; extra == "dev"
Requires-Dist: python-dotenv; extra == "dev"
Requires-Dist: setuptools; extra == "dev"
Requires-Dist: wheel; extra == "dev"
Requires-Dist: twine; extra == "dev"
Requires-Dist: pre-commit; extra == "dev"
Requires-Dist: sphinx; extra == "dev"
Requires-Dist: sphinx_rtd_theme; extra == "dev"
Dynamic: author
Dynamic: author-email
Dynamic: classifier
Dynamic: description
Dynamic: description-content-type
Dynamic: download-url
Dynamic: home-page
Dynamic: keywords
Dynamic: license
Dynamic: license-file
Dynamic: provides-extra
Dynamic: requires-dist
Dynamic: requires-python
Dynamic: summary
